{
  "metadata" : {
    "realm" : null,
    "entityType" : "amDataStoreService",
    "entityId" : "default/dataStoreContainer/policy-store",
    "uid" : "ou=policy-store,ou=dataStoreContainer,ou=default,ou=GlobalConfig,ou=1.0,ou=amDataStoreService,ou=services,ou=am-config",
    "sunServiceID" : "config",
    "objectClass" : [ "sunServiceComponent", "top" ],
    "pathParams" : { },
    "ou" : [ "policy-store" ]
  },
  "data" : {
    "_id" : "default/dataStoreContainer/policy-store",
    "_type" : {
      "_id" : "amDataStoreService",
      "name" : "amDataStoreService",
      "collection" : false
    },
    "bindPassword" : "&{am.stores.policy.password}",
    "useStartTLS" : false,
    "dataStoreEnabled" : {
      "$bool" : "&{am.stores.policy.enabled}"
    },
    "serverUrls" : {
      "$list" : "&{am.stores.policy.servers}"
    },
    "useSsl" : {
      "$bool" : "&{am.stores.policy.ssl.enabled}"
    },
    "bindDN" : "&{am.stores.policy.username}",
    "affinityEnabled" : false
  }
}