{
  "metadata" : {
    "realm" : "/",
    "entityType" : "MailServer",
    "entityId" : "defaultconfig",
    "uid" : "ou=defaultconfig,ou=OrganizationConfig,ou=1.0,ou=MailServer,ou=services,ou=am-config",
    "sunServiceID" : null,
    "objectClass" : [ "organizationalunit", "sunServiceComponent", "top" ],
    "pathParams" : { },
    "ou" : [ "defaultconfig" ]
  },
  "data" : {
    "_id" : "defaultconfig",
    "_type" : {
      "_id" : "MailServer",
      "name" : "MailServer",
      "collection" : false
    },
    "emailAddressAttribute" : "mail",
    "transportType" : null,
    "password" : null,
    "emailRateLimitSeconds" : 1,
    "username" : null,
    "port" : 465,
    "emailImplClassName" : "org.forgerock.openam.services.email.MailServerImpl",
    "message" : null,
    "subject" : null,
    "sslState" : "SSL",
    "from" : null,
    "hostname" : null
  }
}