{
  "metadata" : {
    "realm" : "/",
    "entityType" : "iPlanetAMPolicyService",
    "entityId" : "Condition/UserSelfCheckCondition",
    "uid" : "ou=UserSelfCheckCondition,ou=Condition,ou=PluginConfig,ou=1.0,ou=iPlanetAMPolicyService,ou=services,ou=am-config",
    "sunServiceID" : null,
    "objectClass" : [ "sunService", "top" ],
    "pathParams" : { },
    "ou" : [ "UserSelfCheckCondition" ]
  },
  "data" : {
    "_id" : "Condition/UserSelfCheckCondition",
    "_type" : {
      "_id" : "iPlanetAMPolicyService",
      "name" : "iPlanetAMPolicyService",
      "collection" : false
    }
  }
}