{
  "metadata" : {
    "realm" : "/",
    "entityType" : "EmailTemplateNode",
    "entityId" : "defaultconfig",
    "uid" : "ou=defaultconfig,ou=OrganizationConfig,ou=1.0,ou=EmailTemplateNode,ou=services,ou=am-config",
    "sunServiceID" : null,
    "objectClass" : [ "organizationalunit", "sunServiceComponent", "top" ],
    "pathParams" : { },
    "ou" : [ "defaultconfig" ]
  },
  "data" : {
    "_id" : "defaultconfig",
    "_type" : {
      "_id" : "EmailTemplateNode",
      "name" : "EmailTemplateNode",
      "collection" : false
    }
  }
}